xls2ddl/__init__.py
xls2ddl/json2ddl.py
xls2ddl/json2xlsx.py
xls2ddl/singletree.py
xls2ddl/tmpls.py
xls2ddl/xls2crud.py
xls2ddl/xls2ddl.py
xls2ddl/xls2ui.py
xls2ddl/xlsxData.py
xls2ddl-1.1.2.dist-info/METADATA
xls2ddl-1.1.2.dist-info/WHEEL
xls2ddl-1.1.2.dist-info/entry_points.txt
xls2ddl-1.1.2.dist-info/top_level.txt
xls2ddl-1.1.2.dist-info/RECORD
