Metadata-Version: 2.4
Name: xls2ddl
Version: 1.1.2
Summary: a xlsx file to database ddl converter
Author: "yu moqing"
Author-email: "yumoqing@gmail.com"
License: "MIT"
Requires-Dist: apppublic
